Workbook

Sheet INPUT
B3: Loan Amount | C3: 7000000
B4: Annual Interest Rate (%) | C4: 5
B5: Loan Term (months) | C5: 72
B6: Expected Annual Inflation (%) | C6: 10

Sheet Annuity
D5: Annuity Loan Amortization Schedule
D6: Period | E6: Monthly payment (KZT) | F6: Principal payment (KZT) | G6: Interest payment (KZT) | H6: Outstanding balance (KZT) | K6: Total payment (KZT) | L6: Principal payment (KZT) | M6: Interest payment (KZT)
D7: 1 | E7: =INPUT!$C$3*((INPUT!$C$4/1200)*(1+INPUT!$C$4/1200)^INPUT!$C$5/((1+INPUT!$C$4/1200)^INPUT!$C$5-1)) -> 112734.53 | F7: =E7-G7 -> 83567.862 | G7: =INPUT!C3*INPUT!C4/1200 -> 29166.667 | H7: =INPUT!C3-F7 -> 6916432.1 | J7: Total: | K7: 8116886.1 | L7: 7000000 | M7: 1116886.1
D8: 2 | E8: =INPUT!$C$3*((INPUT!$C$4/1200)*(1+INPUT!$C$4/1200)^INPUT!$C$5/((1+INPUT!$C$4/1200)^INPUT!$C$5-1)) -> 112734.53 | F8: =E8-G8 -> 83916.061 | G8: =H7*INPUT!$C$4/1200 -> 28818.467 | H8: =H7-F8 -> 6832516.1
D9: 3 | E9: =INPUT!$C$3*((INPUT!$C$4/1200)*(1+INPUT!$C$4/1200)^INPUT!$C$5/((1+INPUT!$C$4/1200)^INPUT!$C$5-1)) -> 112734.53 | F9: =E9-G9 -> 84265.712 | G9: =H8*INPUT!$C$4/1200 -> 28468.817 | H9: =H8-F9 -> 6748250.4
D10: 4 | E10: =INPUT!$C$3*((INPUT!$C$4/1200)*(1+INPUT!$C$4/1200)^INPUT!$C$5/((1+INPUT!$C$4/1200)^INPUT!$C$5-1)) -> 112734.53 | F10: =E10-G10 -> 84616.819 | G10: =H9*INPUT!$C$4/1200 -> 28117.71 | H10: =H9-F10 -> 6663633.5
D11: 5 | E11: =INPUT!$C$3*((INPUT!$C$4/1200)*(1+INPUT!$C$4/1200)^INPUT!$C$5/((1+INPUT!$C$4/1200)^INPUT!$C$5-1)) -> 112734.53 | F11: =E11-G11 -> 84969.389 | G11: =H10*INPUT!$C$4/1200 -> 27765.14 | H11: =H10-F11 -> 6578664.2
D12: 6 | E12: =INPUT!$C$3*((INPUT!$C$4/1200)*(1+INPUT!$C$4/1200)^INPUT!$C$5/((1+INPUT!$C$4/1200)^INPUT!$C$5-1)) -> 112734.53 | F12: =E12-G12 -> 85323.428 | G12: =H11*INPUT!$C$4/1200 -> 27411.101 | H12: =H11-F12 -> 6493340.7
D13: 7 | E13: =INPUT!$C$3*((INPUT!$C$4/1200)*(1+INPUT!$C$4/1200)^INPUT!$C$5/((1+INPUT!$C$4/1200)^INPUT!$C$5-1)) -> 112734.53 | F13: =E13-G13 -> 85678.942 | G13: =H12*INPUT!$C$4/1200 -> 27055.586 | H13: =H12-F13 -> 6407661.8
D14: 8 | E14: =INPUT!$C$3*((INPUT!$C$4/1200)*(1+INPUT!$C$4/1200)^INPUT!$C$5/((1+INPUT!$C$4/1200)^INPUT!$C$5-1)) -> 112734.53 | F14: =E14-G14 -> 86035.938 | G14: =H13*INPUT!$C$4/1200 -> 26698.591 | H14: =H13-F14 -> 6321625.8
D15: 9 | E15: =INPUT!$C$3*((INPUT!$C$4/1200)*(1+INPUT!$C$4/1200)^INPUT!$C$5/((1+INPUT!$C$4/1200)^INPUT!$C$5-1)) -> 112734.53 | F15: =E15-G15 -> 86394.421 | G15: =H14*INPUT!$C$4/1200 -> 26340.108 | H15: =H14-F15 -> 6235231.4
D16: 10 | E16: =INPUT!$C$3*((INPUT!$C$4/1200)*(1+INPUT!$C$4/1200)^INPUT!$C$5/((1+INPUT!$C$4/1200)^INPUT!$C$5-1)) -> 112734.53 | F16: =E16-G16 -> 86754.398 | G16: =H15*INPUT!$C$4/1200 -> 25980.131 | H16: =H15-F16 -> 6148477
D17: 11 | E17: =INPUT!$C$3*((INPUT!$C$4/1200)*(1+INPUT!$C$4/1200)^INPUT!$C$5/((1+INPUT!$C$4/1200)^INPUT!$C$5-1)) -> 112734.53 | F17: =E17-G17 -> 87115.874 | G17: =H16*INPUT!$C$4/1200 -> 25618.654 | H17: =H16-F17 -> 6061361.2
D18: 12 | E18: =INPUT!$C$3*((INPUT!$C$4/1200)*(1+INPUT!$C$4/1200)^INPUT!$C$5/((1+INPUT!$C$4/1200)^INPUT!$C$5-1)) -> 112734.53 | F18: =E18-G18 -> 87478.857 | G18: =H17*INPUT!$C$4/1200 -> 25255.671 | H18: =H17-F18 -> 5973882.3
D19: 13 | E19: =INPUT!$C$3*((INPUT!$C$4/1200)*(1+INPUT!$C$4/1200)^INPUT!$C$5/((1+INPUT!$C$4/1200)^INPUT!$C$5-1)) -> 112734.53 | F19: =E19-G19 -> 87843.352 | G19: =H18*INPUT!$C$4/1200 -> 24891.176 | H19: =H18-F19 -> 5886038.9
... D78: 72 | E78: =INPUT!$C$3*((INPUT!$C$4/1200)*(1+INPUT!$C$4/1200)^INPUT!$C$5/((1+INPUT!$C$4/1200)^INPUT!$C$5-1)) -> 112734.53 | F78: =E78-G78 -> 112266.75 | G78: =H77*INPUT!$C$4/1200 -> 467.77813 | H78: =H77-F78 -> 3.2261596e-08
D79: Total: | E79: =SUM(E7:E78) -> 8116886.1 | F79: =SUM(F7:F78) -> 7000000 | G79: =SUM(G7:G78) -> 1116886.1

Sheet Differentiated
D5: Differentiated Loan Amortization Schedule
D6: Period | E6: Monthly payment (KZT) | F6: Principal payment (KZT) | G6: Interest payment (KZT) | H6: Outstanding balance (KZT) | K6: Total payment (KZT) | L6: Principal payment (KZT) | M6: Interest payment (KZT)
D7: 1 | E7: =INPUT!$C$3/INPUT!$C$5+(INPUT!$C$3-(INPUT!$C$3/INPUT!$C$5)*(D7-1))*INPUT!$C$4/1200 -> 126388.89 | F7: =E7-G7 -> 97222.222 | G7: =INPUT!C3*INPUT!C4/1200 -> 29166.667 | H7: =INPUT!C3-F7 -> 6902777.8 | J7: Total: | K7: 8064583.3 | L7: 7000000 | M7: 1064583.3
D8: 2 | E8: =INPUT!$C$3/INPUT!$C$5+(INPUT!$C$3-(INPUT!$C$3/INPUT!$C$5)*(D8-1))*INPUT!$C$4/1200 -> 125983.8 | F8: =E8-G8 -> 97222.222 | G8: =H7*INPUT!$C$4/1200 -> 28761.574 | H8: =H7-F8 -> 6805555.6
D9: 3 | E9: =INPUT!$C$3/INPUT!$C$5+(INPUT!$C$3-(INPUT!$C$3/INPUT!$C$5)*(D9-1))*INPUT!$C$4/1200 -> 125578.7 | F9: =E9-G9 -> 97222.222 | G9: =H8*INPUT!$C$4/1200 -> 28356.481 | H9: =H8-F9 -> 6708333.3
D10: 4 | E10: =INPUT!$C$3/INPUT!$C$5+(INPUT!$C$3-(INPUT!$C$3/INPUT!$C$5)*(D10-1))*INPUT!$C$4/1200 -> 125173.61 | F10: =E10-G10 -> 97222.222 | G10: =H9*INPUT!$C$4/1200 -> 27951.389 | H10: =H9-F10 -> 6611111.1
D11: 5 | E11: =INPUT!$C$3/INPUT!$C$5+(INPUT!$C$3-(INPUT!$C$3/INPUT!$C$5)*(D11-1))*INPUT!$C$4/1200 -> 124768.52 | F11: =E11-G11 -> 97222.222 | G11: =H10*INPUT!$C$4/1200 -> 27546.296 | H11: =H10-F11 -> 6513888.9
D12: 6 | E12: =INPUT!$C$3/INPUT!$C$5+(INPUT!$C$3-(INPUT!$C$3/INPUT!$C$5)*(D12-1))*INPUT!$C$4/1200 -> 124363.43 | F12: =E12-G12 -> 97222.222 | G12: =H11*INPUT!$C$4/1200 -> 27141.204 | H12: =H11-F12 -> 6416666.7
D13: 7 | E13: =INPUT!$C$3/INPUT!$C$5+(INPUT!$C$3-(INPUT!$C$3/INPUT!$C$5)*(D13-1))*INPUT!$C$4/1200 -> 123958.33 | F13: =E13-G13 -> 97222.222 | G13: =H12*INPUT!$C$4/1200 -> 26736.111 | H13: =H12-F13 -> 6319444.4
D14: 8 | E14: =INPUT!$C$3/INPUT!$C$5+(INPUT!$C$3-(INPUT!$C$3/INPUT!$C$5)*(D14-1))*INPUT!$C$4/1200 -> 123553.24 | F14: =E14-G14 -> 97222.222 | G14: =H13*INPUT!$C$4/1200 -> 26331.019 | H14: =H13-F14 -> 6222222.2
D15: 9 | E15: =INPUT!$C$3/INPUT!$C$5+(INPUT!$C$3-(INPUT!$C$3/INPUT!$C$5)*(D15-1))*INPUT!$C$4/1200 -> 123148.15 | F15: =E15-G15 -> 97222.222 | G15: =H14*INPUT!$C$4/1200 -> 25925.926 | H15: =H14-F15 -> 6125000
D16: 10 | E16: =INPUT!$C$3/INPUT!$C$5+(INPUT!$C$3-(INPUT!$C$3/INPUT!$C$5)*(D16-1))*INPUT!$C$4/1200 -> 122743.06 | F16: =E16-G16 -> 97222.222 | G16: =H15*INPUT!$C$4/1200 -> 25520.833 | H16: =H15-F16 -> 6027777.8
D17: 11 | E17: =INPUT!$C$3/INPUT!$C$5+(INPUT!$C$3-(INPUT!$C$3/INPUT!$C$5)*(D17-1))*INPUT!$C$4/1200 -> 122337.96 | F17: =E17-G17 -> 97222.222 | G17: =H16*INPUT!$C$4/1200 -> 25115.741 | H17: =H16-F17 -> 5930555.6
D18: 12 | E18: =INPUT!$C$3/INPUT!$C$5+(INPUT!$C$3-(INPUT!$C$3/INPUT!$C$5)*(D18-1))*INPUT!$C$4/1200 -> 121932.87 | F18: =E18-G18 -> 97222.222 | G18: =H17*INPUT!$C$4/1200 -> 24710.648 | H18: =H17-F18 -> 5833333.3
D19: 13 | E19: =INPUT!$C$3/INPUT!$C$5+(INPUT!$C$3-(INPUT!$C$3/INPUT!$C$5)*(D19-1))*INPUT!$C$4/1200 -> 121527.78 | F19: =E19-G19 -> 97222.222 | G19: =H18*INPUT!$C$4/1200 -> 24305.556 | H19: =H18-F19 -> 5736111.1
... D78: 72 | E78: =INPUT!$C$3/INPUT!$C$5+(INPUT!$C$3-(INPUT!$C$3/INPUT!$C$5)*(D78-1))*INPUT!$C$4/1200 -> 97627.315 | F78: =E78-G78 -> 97222.222 | G78: =H77*INPUT!$C$4/1200 -> 405.09259 | H78: =H77-F78 -> 1.0622898e-08
D79: Total: | E79: =SUM(E7:E78) -> 8064583.3 | F79: =SUM(F7:F78) -> 7000000 | G79: =SUM(G7:G78) -> 1064583.3

Sheet Analysis
D5: Discounted Cash Flow Analysis | J5: TOTAL PAYMENTS | N5: Sensitivity Analysis: Interest Rate vs Inflation
D6: Period | E6: Annuity Payment | F6: Annuity PV | G6: Diff Payment | H6: Diff PV | J6: Nominal Total | K6: Annuity: | L6: =E79 -> 8116886.1 | N6: Annual Interest Rate (%): | O6: 10
D7: 1 | E7: =Annuity!E7 -> 112734.53 | F7: =E7/((1+INPUT!$C$6/1200)^D7) -> 111802.84 | G7: =Differentiated!E7 -> 126388.89 | H7: =G7/((1+INPUT!$C$6/1200)^D7) -> 125344.35 | K7: Differentiated: | L7: =G79 -> 8064583.3 | N7: Expected Annual Inflation (%): | O7: 15
D8: 2 | E8: =Annuity!E8 -> 112734.53 | F8: =E8/((1+INPUT!$C$6/1200)^D8) -> 110878.85 | G8: =Differentiated!E8 -> 125983.8 | H8: =G8/((1+INPUT!$C$6/1200)^D8) -> 123910.02 | J8: Discounted Total (PV) | K8: Annuity: | L8: =F79 -> 6085259.4 | N8: Difference of discounted total cost: | O8: -66364
D9: 3 | E9: =Annuity!E9 -> 112734.53 | F9: =E9/((1+INPUT!$C$6/1200)^D9) -> 109962.49 | G9: =Differentiated!E9 -> 125578.7 | H9: =G9/((1+INPUT!$C$6/1200)^D9) -> 122490.84 | K9: Differentiated: | L9: =H79 -> 6123962.9 | N9: Difference of nominal total cost: | O9: 207856
D10: 4 | E10: =Annuity!E10 -> 112734.53 | F10: =E10/((1+INPUT!$C$6/1200)^D10) -> 109053.71 | G10: =Differentiated!E10 -> 125173.61 | H10: =G10/((1+INPUT!$C$6/1200)^D10) -> 121086.66 | J10: Difference of nominal total cost: | L10: =L6-L7 -> 52302.728
D11: 5 | E11: =Annuity!E11 -> 112734.53 | F11: =E11/((1+INPUT!$C$6/1200)^D11) -> 108152.44 | G11: =Differentiated!E11 -> 124768.52 | H11: =G11/((1+INPUT!$C$6/1200)^D11) -> 119697.31 | J11: Difference of discounted total cost: | L11: =L8-L9 -> -38703.496 | N11: Annual Interest Rate (%): | O11: 3
D12: 6 | E12: =Annuity!E12 -> 112734.53 | F12: =E12/((1+INPUT!$C$6/1200)^D12) -> 107258.62 | G12: =Differentiated!E12 -> 124363.43 | H12: =G12/((1+INPUT!$C$6/1200)^D12) -> 118322.66 | N12: Expected Annual Inflation (%): | O12: 8
D13: 7 | E13: =Annuity!E13 -> 112734.53 | F13: =E13/((1+INPUT!$C$6/1200)^D13) -> 106372.19 | G13: =Differentiated!E13 -> 123958.33 | H13: =G13/((1+INPUT!$C$6/1200)^D13) -> 116962.56 | N13: Difference of discounted total cost: | O13: -24691
D14: 8 | E14: =Annuity!E14 -> 112734.53 | F14: =E14/((1+INPUT!$C$6/1200)^D14) -> 105493.08 | G14: =Differentiated!E14 -> 123553.24 | H14: =G14/((1+INPUT!$C$6/1200)^D14) -> 115616.85 | N14: Difference of nominal total cost: | O14: 18863
D15: 9 | E15: =Annuity!E15 -> 112734.53 | F15: =E15/((1+INPUT!$C$6/1200)^D15) -> 104621.23 | G15: =Differentiated!E15 -> 123148.15 | H15: =G15/((1+INPUT!$C$6/1200)^D15) -> 114285.4
D16: 10 | E16: =Annuity!E16 -> 112734.53 | F16: =E16/((1+INPUT!$C$6/1200)^D16) -> 103756.59 | G16: =Differentiated!E16 -> 122743.06 | H16: =G16/((1+INPUT!$C$6/1200)^D16) -> 112968.06 | N16: Annual Interest Rate (%): | O16: 5
D17: 11 | E17: =Annuity!E17 -> 112734.53 | F17: =E17/((1+INPUT!$C$6/1200)^D17) -> 102899.1 | G17: =Differentiated!E17 -> 122337.96 | H17: =G17/((1+INPUT!$C$6/1200)^D17) -> 111664.69 | N17: Expected Annual Inflation (%): | O17: 5
D18: 12 | E18: =Annuity!E18 -> 112734.53 | F18: =E18/((1+INPUT!$C$6/1200)^D18) -> 102048.7 | G18: =Differentiated!E18 -> 121932.87 | H18: =G18/((1+INPUT!$C$6/1200)^D18) -> 110375.15 | N18: Difference of discounted total cost: | O18: 0
D19: 13 | E19: =Annuity!E19 -> 112734.53 | F19: =E19/((1+INPUT!$C$6/1200)^D19) -> 101205.32 | G19: =Differentiated!E19 -> 121527.78 | H19: =G19/((1+INPUT!$C$6/1200)^D19) -> 109099.29 | N19: Difference of nominal total cost: | O19: 52303
D20: 14 | E20: =Annuity!E20 -> 112734.53 | F20: =E20/((1+INPUT!$C$6/1200)^D20) -> 100368.91 | G20: =Differentiated!E20 -> 121122.69 | H20: =G20/((1+INPUT!$C$6/1200)^D20) -> 107836.99
D21: 15 | E21: =Annuity!E21 -> 112734.53 | F21: =E21/((1+INPUT!$C$6/1200)^D21) -> 99539.416 | G21: =Differentiated!E21 -> 120717.59 | H21: =G21/((1+INPUT!$C$6/1200)^D21) -> 106588.1 | N21: Annual Interest Rate (%): | O21: 8
D22: 16 | E22: =Annuity!E22 -> 112734.53 | F22: =E22/((1+INPUT!$C$6/1200)^D22) -> 98716.776 | G22: =Differentiated!E22 -> 120312.5 | H22: =G22/((1+INPUT!$C$6/1200)^D22) -> 105352.48 | N22: Expected Annual Inflation (%): | O22: 3
D23: 17 | E23: =Annuity!E23 -> 112734.53 | F23: =E23/((1+INPUT!$C$6/1200)^D23) -> 97900.935 | G23: =Differentiated!E23 -> 119907.41 | H23: =G23/((1+INPUT!$C$6/1200)^D23) -> 104130.01 | N23: Difference of discounted total cost: | O23: 75982
D24: 18 | E24: =Annuity!E24 -> 112734.53 | F24: =E24/((1+INPUT!$C$6/1200)^D24) -> 97091.837 | G24: =Differentiated!E24 -> 119502.31 | H24: =G24/((1+INPUT!$C$6/1200)^D24) -> 102920.55 | N24: Difference of nominal total cost: | O24: 133420
D25: 19 | E25: =Annuity!E25 -> 112734.53 | F25: =E25/((1+INPUT!$C$6/1200)^D25) -> 96289.425 | G25: =Differentiated!E25 -> 119097.22 | H25: =G25/((1+INPUT!$C$6/1200)^D25) -> 101723.96
D26: 20 | E26: =Annuity!E26 -> 112734.53 | F26: =E26/((1+INPUT!$C$6/1200)^D26) -> 95493.644 | G26: =Differentiated!E26 -> 118692.13 | H26: =G26/((1+INPUT!$C$6/1200)^D26) -> 100540.13 | N26: Annual Interest Rate (%): | O26: 15
D27: 21 | E27: =Annuity!E27 -> 112734.53 | F27: =E27/((1+INPUT!$C$6/1200)^D27) -> 94704.441 | G27: =Differentiated!E27 -> 118287.04 | H27: =G27/((1+INPUT!$C$6/1200)^D27) -> 99368.914 | N27: Expected Annual Inflation (%): | O27: 10
D28: 22 | E28: =Annuity!E28 -> 112734.53 | F28: =E28/((1+INPUT!$C$6/1200)^D28) -> 93921.759 | G28: =Differentiated!E28 -> 117881.94 | H28: =G28/((1+INPUT!$C$6/1200)^D28) -> 98210.191 | N28: Difference of discounted total cost: | O28: 113620
D29: 23 | E29: =Annuity!E29 -> 112734.53 | F29: =E29/((1+INPUT!$C$6/1200)^D29) -> 93145.546 | G29: =Differentiated!E29 -> 117476.85 | H29: =G29/((1+INPUT!$C$6/1200)^D29) -> 97063.834 | N29: Difference of nominal total cost: | O29: 463337
D30: 24 | E30: =Annuity!E30 -> 112734.53 | F30: =E30/((1+INPUT!$C$6/1200)^D30) -> 92375.749 | G30: =Differentiated!E30 -> 117071.76 | H30: =G30/((1+INPUT!$C$6/1200)^D30) -> 95929.717
D31: 25 | E31: =Annuity!E31 -> 112734.53 | F31: =E31/((1+INPUT!$C$6/1200)^D31) -> 91612.313 | G31: =Differentiated!E31 -> 116666.67 | H31: =G31/((1+INPUT!$C$6/1200)^D31) -> 94807.716
D32: 26 | E32: =Annuity!E32 -> 112734.53 | F32: =E32/((1+INPUT!$C$6/1200)^D32) -> 90855.186 | G32: =Differentiated!E32 -> 116261.57 | H32: =G32/((1+INPUT!$C$6/1200)^D32) -> 93697.708
D33: 27 | E33: =Annuity!E33 -> 112734.53 | F33: =E33/((1+INPUT!$C$6/1200)^D33) -> 90104.317 | G33: =Differentiated!E33 -> 115856.48 | H33: =G33/((1+INPUT!$C$6/1200)^D33) -> 92599.572
D34: 28 | E34: =Annuity!E34 -> 112734.53 | F34: =E34/((1+INPUT!$C$6/1200)^D34) -> 89359.653 | G34: =Differentiated!E34 -> 115451.39 | H34: =G34/((1+INPUT!$C$6/1200)^D34) -> 91513.187
D35: 29 | E35: =Annuity!E35 -> 112734.53 | F35: =E35/((1+INPUT!$C$6/1200)^D35) -> 88621.143 | G35: =Differentiated!E35 -> 115046.3 | H35: =G35/((1+INPUT!$C$6/1200)^D35) -> 90438.435
D36: 30 | E36: =Annuity!E36 -> 112734.53 | F36: =E36/((1+INPUT!$C$6/1200)^D36) -> 87888.737 | G36: =Differentiated!E36 -> 114641.2 | H36: =G36/((1+INPUT!$C$6/1200)^D36) -> 89375.196
D37: 31 | E37: =Annuity!E37 -> 112734.53 | F37: =E37/((1+INPUT!$C$6/1200)^D37) -> 87162.384 | G37: =Differentiated!E37 -> 114236.11 | H37: =G37/((1+INPUT!$C$6/1200)^D37) -> 88323.355
D38: 32 | E38: =Annuity!E38 -> 112734.53 | F38: =E38/((1+INPUT!$C$6/1200)^D38) -> 86442.034 | G38: =Differentiated!E38 -> 113831.02 | H38: =G38/((1+INPUT!$C$6/1200)^D38) -> 87282.795
D39: 33 | E39: =Annuity!E39 -> 112734.53 | F39: =E39/((1+INPUT!$C$6/1200)^D39) -> 85727.637 | G39: =Differentiated!E39 -> 113425.93 | H39: =G39/((1+INPUT!$C$6/1200)^D39) -> 86253.402
D40: 34 | E40: =Annuity!E40 -> 112734.53 | F40: =E40/((1+INPUT!$C$6/1200)^D40) -> 85019.144 | G40: =Differentiated!E40 -> 113020.83 | H40: =G40/((1+INPUT!$C$6/1200)^D40) -> 85235.062
D41: 35 | E41: =Annuity!E41 -> 112734.53 | F41: =E41/((1+INPUT!$C$6/1200)^D41) -> 84316.506 | G41: =Differentiated!E41 -> 112615.74 | H41: =G41/((1+INPUT!$C$6/1200)^D41) -> 84227.663
... D78: 72 | E78: =Annuity!E78 -> 112734.53 | F78: =E78/((1+INPUT!$C$6/1200)^D78) -> 62024.034 | G78: =Differentiated!E78 -> 97627.315 | H78: =G78/((1+INPUT!$C$6/1200)^D78) -> 53712.38
D79: Total: | E79: =SUM(E7:E78) -> 8116886.1 | F79: =SUM(F7:F78) -> 6085259.4 | G79: =SUM(G7:G78) -> 8064583.3 | H79: =SUM(H7:H78) -> 6123962.9
